castella_skia/__init__.py
castella_skia/__init__.pyi
castella_skia/castella_skia.cpython-312-aarch64-linux-gnu.so
castella_skia-0.1.4.dist-info/METADATA
castella_skia-0.1.4.dist-info/WHEEL
castella_skia.libs/libbrotlicommon-016600f6.so.1
castella_skia.libs/libbrotlidec-b7895f0f.so.1
castella_skia.libs/libbz2-89a72a98.so.1.0
castella_skia.libs/libfontconfig-82c60a33.so.1
castella_skia.libs/libfreetype-a73e51b0.so.6
castella_skia.libs/libpng16-649ac371.so.16
castella_skia-0.1.4.dist-info/RECORD
