Metadata-Version: 2.4
Name: castella-skia
Version: 0.1.4
Classifier: Development Status :: 3 - Alpha
Classifier: Intended Audience :: Developers
Classifier: License :: OSI Approved :: MIT License
Classifier: Operating System :: OS Independent
Classifier: Programming Language :: Python :: 3
Classifier: Programming Language :: Python :: 3.10
Classifier: Programming Language :: Python :: 3.11
Classifier: Programming Language :: Python :: 3.12
Classifier: Programming Language :: Python :: 3.13
Classifier: Programming Language :: Python :: 3.14
Classifier: Programming Language :: Rust
Classifier: Topic :: Multimedia :: Graphics
Classifier: Topic :: Software Development :: User Interfaces
Summary: Unified Skia rendering backend for Castella UI framework
Keywords: gui,ui,skia,graphics,cross-platform
Author-email: Yasushi Itoh <i2y@icloud.com>
License: MIT
Requires-Python: >=3.10
Project-URL: Documentation, https://i2y.github.io/castella
Project-URL: Homepage, https://github.com/i2y/castella
Project-URL: Repository, https://github.com/i2y/castella
